ibapi/__init__.py
ibapi/account_summary_tags.py
ibapi/client.py
ibapi/comm.py
ibapi/commission_report.py
ibapi/common.py
ibapi/connection.py
ibapi/contract.py
ibapi/decoder.py
ibapi/enum_implem.py
ibapi/errors.py
ibapi/execution.py
ibapi/message.py
ibapi/news.py
ibapi/object_implem.py
ibapi/order.py
ibapi/order_condition.py
ibapi/order_state.py
ibapi/orderdecoder.py
ibapi/reader.py
ibapi/scanner.py
ibapi/server_versions.py
ibapi/softdollartier.py
ibapi/tag_value.py
ibapi/ticktype.py
ibapi/utils.py
ibapi/wrapper.py
TwsIBapi_projectX_IB-10.11.1.1.dist-info/LICENSE
TwsIBapi_projectX_IB-10.11.1.1.dist-info/METADATA
TwsIBapi_projectX_IB-10.11.1.1.dist-info/WHEEL
TwsIBapi_projectX_IB-10.11.1.1.dist-info/top_level.txt
TwsIBapi_projectX_IB-10.11.1.1.dist-info/RECORD
